README.md
setup.py
sphinx_autodoc_construct/__init__.py
sphinx_autodoc_construct.egg-info/PKG-INFO
sphinx_autodoc_construct.egg-info/SOURCES.txt
sphinx_autodoc_construct.egg-info/dependency_links.txt
sphinx_autodoc_construct.egg-info/requires.txt
sphinx_autodoc_construct.egg-info/top_level.txt
sphinx_autodoc_construct/_static/sphinx-autodoc-construct.css