Metadata-Version: 2.1
Name: sphinx-autodoc-construct
Version: 0.1.0
Summary: A Sphinx extension to automatically document your Contruct structs.
Home-page: https://github.com/maxdup/sphinx-autodoc-construct
Author: Maxime Dupuis
Author-email: mdupuis@hotmail.ca
License: gpl-3.0
Classifier: Development Status :: 4 - Beta
Classifier: Intended Audience :: Developers
Classifier: Topic :: Documentation
Classifier: Topic :: Software Development
Classifier: Topic :: Utilities
Classifier: License :: OSI Approved :: GNU General Public License v3 (GPLv3)
Classifier: Programming Language :: Python :: 3
Classifier: Operating System :: OS Independent
Classifier: Framework :: Sphinx :: Extension
